tinkertown/__init__.py
tinkertown/__main__.py
tinkertown/technician.py
tinkertown_technician-0.2.1.dist-info/entry_points.txt
tinkertown_technician-0.2.1.dist-info/WHEEL
tinkertown_technician-0.2.1.dist-info/METADATA
tinkertown_technician-0.2.1.dist-info/RECORD
