Metadata-Version: 2.1
Name: tinkertown-technician
Version: 0.2.1
Summary: Tinkertown Technician -- Battlecry: Fix your Heartstone Deck Tracker
License: GPL-3.0-or-later
Author-email: Chris Wesseling <chris.wesseling@xs4all.nl>
Requires-Python: >=3.7
Classifier: License :: OSI Approved :: GNU General Public License v3 or later (GPLv3+)
Classifier: Programming Language :: Python :: 3
Classifier: Programming Language :: Python :: 3.7
Classifier: Programming Language :: Python :: 3.8
Classifier: Programming Language :: Python :: 3.9
Requires-Dist: psutil~=5.8
Requires-Dist: requests
Requires-Dist: toml~=0.10
Requires-Dist: typer
Requires-Dist: watchdog
Project-URL: homepage, https://github.com/CharString/tinkertown-technician
